sportnews/__init__.py
sportnews/client.py
sportnews/exceptions.py
sportnews/models.py
sportnews_api-0.1.8.dist-info/LICENSE
sportnews_api-0.1.8.dist-info/METADATA
sportnews_api-0.1.8.dist-info/WHEEL
sportnews_api-0.1.8.dist-info/top_level.txt
sportnews_api-0.1.8.dist-info/RECORD
