Metadata-Version: 2.1
Name: sportnews-api
Version: 0.1.8
Summary: Official Python SDK for the SportNews API - Access sports news in real time
Home-page: https://github.com/votre-username/sportnews-sdk
Author: Stefen
Author-email: votre.email@domain.com
Project-URL: Documentation, https://docs.sportnews-api.com
Project-URL: Source, https://github.com/votre-username/sportnews-sdk
Keywords: sports news api sdk actualités sportives
Classifier: Development Status :: 3 - Alpha
Classifier: Intended Audience :: Developers
Classifier: License :: OSI Approved :: MIT License
Classifier: Operating System :: OS Independent
Classifier: Programming Language :: Python :: 3
Classifier: Programming Language :: Python :: 3.7
Classifier: Programming Language :: Python :: 3.8
Classifier: Programming Language :: Python :: 3.9
Classifier: Topic :: Software Development :: Libraries :: Python Modules
Classifier: Topic :: Internet :: WWW/HTTP
Requires-Python: >=3.9
License-File: LICENSE
Requires-Dist: requests>=2.25.0
